[
	{
		"__TYPE__": "SharedSliceContent",
		"variation": "default",
		"primary": {
			"about_text": {
				"__TYPE__": "StructuredTextContent",
				"value": [
					{
						"type": "paragraph",
						"content": {
							"text": "Eiusmod sunt esse consequat."
						}
					}
				]
			},
			"about_link": {
				"key": "93ea3e45-26b9-43f6-97e0-e47d4e69f5ad",
				"__TYPE__": "LinkContent",
				"value": {
					"__TYPE__": "ExternalLink",
					"url": "http://google.com",
					"text": "invented"
				}
			},
			"featured_image": {
				"origin": {
					"id": "main",
					"url": "https://images.unsplash.com/photo-1551739440-5dd934d3a94a",
					"width": 3456,
					"height": 4320
				},
				"url": "https://images.unsplash.com/photo-1551739440-5dd934d3a94a",
				"width": 3456,
				"height": 4320,
				"edit": {
					"zoom": 1,
					"crop": {
						"x": 0,
						"y": 0
					},
					"background": "transparent"
				},
				"alt": "happen",
				"credits": null,
				"__TYPE__": "ImageContent",
				"thumbnails": {}
			},
			"featured_text": {
				"__TYPE__": "StructuredTextContent",
				"value": [
					{
						"type": "heading1",
						"content": {
							"text": "Block"
						}
					}
				]
			},
			"featured_link": {
				"__TYPE__": "LinkContent",
				"key": "c9da9953-a8fe-45cd-afe7-af1e02065611",
				"value": {
					"__TYPE__": "ExternalLink",
					"url": "http://twitter.com",
					"text": "ought"
				}
			}
		},
		"items": []
	}
]